{
  "context_id": "ctx-dc97c52d-18b3-43d2-bb51-2b8df0229ea0",
  "schema_version": "jh:0.3",
  "producer": "did:university:ingestion-agent",
  "created_at": "2026-04-26T11:33:19.006691+00:00",
  "ttl": "P30D",
  "status": "active",
  "scope": "education_assessment",
  "semantic_payload": [
    {
      "@model": "UserML",
      "mainpart": {
        "subject": "submission:S-98765",
        "auxiliary": "hasProperty",
        "predicate": "essay_word_count",
        "range": "non-negative-integer",
        "object": 1527
      },
      "administration": {
        "group": "Observation"
      }
    },
    {
      "@model": "UserML",
      "mainpart": {
        "subject": "submission:S-98765",
        "auxiliary": "hasProperty",
        "predicate": "essay_topic",
        "range": "EssayTopicEnum",
        "object": "climate_policy"
      },
      "administration": {
        "group": "Observation"
      }
    },
    {
      "@model": "UserML",
      "mainpart": {
        "subject": "submission:S-98765",
        "auxiliary": "hasProperty",
        "predicate": "rubric_version",
        "range": "RubricVersionURI",
        "object": "ENG101-v3"
      },
      "administration": {
        "group": "Observation"
      }
    }
  ],
  "artifacts_registry": [
    {
      "artifact_id": "art-essay-text",
      "type": "token_sequence",
      "content_hash": "sha256:1111aaaa2222bbbb3333cccc4444dddd5555eeee6666ffff7777aaaa8888bbbb",
      "timestamp": "2026-04-26T11:33:19.006835+00:00",
      "deterministic": false,
      "metadata": {}
    },
    {
      "artifact_id": "art-rubric",
      "type": "token_sequence",
      "content_hash": "sha256:2222bbbb3333cccc4444dddd5555eeee6666ffff7777aaaa8888bbbb9999cccc",
      "timestamp": "2026-04-26T11:33:19.006861+00:00",
      "deterministic": false,
      "metadata": {}
    },
    {
      "artifact_id": "art-grade-result",
      "type": "semantic_extraction",
      "content_hash": "sha256:3333cccc4444dddd5555eeee6666ffff7777aaaa8888bbbb9999ccccaaaadddd",
      "model": "essay-grader-v2",
      "timestamp": "2026-04-26T11:33:19.007938+00:00",
      "deterministic": false,
      "confidence": 0.91,
      "metadata": {}
    }
  ],
  "passed_artifact_pointer": "art-grade-result",
  "decision_influence": [
    {
      "agent": "essay-grading-agent",
      "categories": [
        "argument_quality",
        "evidence_use",
        "writing_clarity",
        "critical_thinking"
      ],
      "abstraction_level": "interpretation",
      "temporal_scope": "current",
      "influence_weights": {
        "argument_quality": 0.3,
        "evidence_use": 0.3,
        "writing_clarity": 0.2,
        "critical_thinking": 0.2
      },
      "confidence": 0.91
    }
  ],
  "privacy": {
    "data_category": "behavioral",
    "legal_basis": "legitimate_interest",
    "retention": "P1Y",
    "storage_policy": "university-encrypted",
    "feature_suppression": [
      "student_name",
      "student_id",
      "accommodation_flags",
      "prior_grades"
    ],
    "pii_detached": true
  },
  "compliance": {
    "risk_level": "high",
    "human_oversight_required": false,
    "forwarding_policy": "semantic_forward",
    "model_card_ref": "https://university.example/models/essay-grader-v2",
    "test_suite_ref": "https://university.example/fairness-tests/2026-Q1",
    "escalation_path": "academic-affairs@university.example"
  },
  "provenance_ref": {
    "prov_graph_id": "prov:ctx-edu-grading-001",
    "prov_digest": "e60b3e0d45467800e07c1f5565105918533b81232739b5805f39738465419729"
  },
  "proof": {
    "canonicalization": "URDNA2015",
    "content_hash": "bf9921d2d93b38324e8582d31f431d20abd3a281f39566ae1a0b140d8d712952",
    "signature": "c8b5f62504aaad03a8268e6edec752e2f5caf0bf950a576b83b0aed0614f32f0",
    "signer": "did:university:compliance-officer"
  },
  "@context": {
    "jh": "https://jhcontext.com/vocab#",
    "prov": "http://www.w3.org/ns/prov#",
    "xsd": "http://www.w3.org/2001/XMLSchema#"
  },
  "@type": "jh:Envelope"
}